ancypwn_terminal_iterm2/__init__.py
ancypwn_terminal_iterm2/iterm2.py
ancypwn_terminal_iterm2-0.0.1.dist-info/METADATA
ancypwn_terminal_iterm2-0.0.1.dist-info/WHEEL
ancypwn_terminal_iterm2-0.0.1.dist-info/top_level.txt
ancypwn_terminal_iterm2-0.0.1.dist-info/RECORD
